{
  "center": {
    "description": "All servos at the calibrated neutral point.",
    "setpoints": [0.0, 0.0, 0.0, 0.0, 0.0, 0.0, 0.0, 0.0]
  },
  "stretch": {
    "description": "legs to maximum extension.",
    "setpoints": [0.0, -1.0, 0.0, -1.0, 0.0, -1.0, 0.0, 1.0]
  },
  "folded": {
    "description": "Folded pose.",
    "setpoints": [1.0, 1.0, -1.0, 1.0, -1.0, 1.0, 1.0, -1.0]
  },
  "stand": {
    "description": "Approximate stand pose.",
    "setpoints": [0.3, 1.0, 0.4, -1.0, -0.3, -1.0, 0.3, 1.0]
  }
}
